{"timestamp":"2019-11-01T13:27:00.000Z","data":{"system":{"power":{"units":"kW","value":350},"savings":{"units":"%","value":0.10000000000000016}},"workstations":[{"id":0,"active":true,"diameter":{"value":247.63263436258595,"units":"mm"},"airVelocity":{"value":11.031542796558977,"units":"m/s"}},{"id":1,"active":true,"diameter":{"value":129.9062083646242,"units":"mm"},"airVelocity":{"value":50.66816581394131,"units":"m/s"}},{"id":2,"active":false,"diameter":{"value":132.11168765629733,"units":"mm"},"airVelocity":{"value":0,"units":"m/s"}},{"id":3,"active":true,"diameter":{"value":479.22224739557464,"units":"mm"},"airVelocity":{"value":28.00210341380085,"units":"m/s"}},{"id":4,"active":true,"diameter":{"value":397.86718811907343,"units":"mm"},"airVelocity":{"value":41.65527526606571,"units":"m/s"}},{"id":5,"active":true,"diameter":{"value":335.3900363931166,"units":"mm"},"airVelocity":{"value":35.90584244921706,"units":"m/s"}},{"id":6,"active":true,"diameter":{"value":340.74741589363964,"units":"mm"},"airVelocity":{"value":35.9920700883374,"units":"m/s"}},{"id":7,"active":true,"diameter":{"value":287.91244442825416,"units":"mm"},"airVelocity":{"value":29.110622120033863,"units":"m/s"}},{"id":8,"active":true,"diameter":{"value":155.0909468854058,"units":"mm"},"airVelocity":{"value":42.089620570359635,"units":"m/s"}},{"id":9,"active":true,"diameter":{"value":384.00207641521524,"units":"mm"},"airVelocity":{"value":36.55011358307147,"units":"m/s"}}]}}